bbog_sg_python_redis_lib/__init__.py
bbog_sg_python_redis_lib/config.py
bbog_sg_python_redis_lib/redis_utils.py
bbog_sg_python_redis_lib/models/__init__.py
bbog_sg_python_redis_lib/models/http_method_enum.py
bbog_sg_python_redis_lib/models/time_unit_enum.py
bbog_sg_python_redis_lib/utils/__init__.py
bbog_sg_python_redis_lib/utils/logging_utils.py
bbog_sg_python_redis_lib/utils/url_builder.py
bbog_sg_python_redis_lib/utils/url_builder_v1.py
bbog_sg_python_redis_lib-0.0.12.dist-info/METADATA
bbog_sg_python_redis_lib-0.0.12.dist-info/WHEEL
bbog_sg_python_redis_lib-0.0.12.dist-info/top_level.txt
bbog_sg_python_redis_lib-0.0.12.dist-info/RECORD
