Metadata-Version: 2.1
Name: bbog-sg-python-redis-lib
Version: 0.0.12
Summary: Python library to handle redis api
Home-page: UNKNOWN
Author: otacha@bancodebogota.com.co
Author-email: UNKNOWN
License: MIT
Platform: UNKNOWN
Classifier: Development Status :: 4 - Beta
Classifier: Intended Audience :: Developers
Classifier: Topic :: Software Development :: Build Tools
Classifier: License :: OSI Approved :: MIT License
Classifier: Programming Language :: Python :: 3.7
Classifier: Programming Language :: Python :: 3.8
Classifier: Programming Language :: Python :: 3.9
Requires-Dist: requests (==2.25.1)
